uk_geo_utils/__init__.py
uk_geo_utils/base_importer.py
uk_geo_utils/geocoders.py
uk_geo_utils/helpers.py
uk_geo_utils/models.py
uk_geo_utils/management/__init__.py
uk_geo_utils/management/commands/__init__.py
uk_geo_utils/management/commands/clean_addressbase_plus.py
uk_geo_utils/management/commands/clean_addressbase_standard.py
uk_geo_utils/management/commands/import_cleaned_addresses.py
uk_geo_utils/management/commands/import_onspd.py
uk_geo_utils/management/commands/import_onsud.py
uk_geo_utils/migrations/0001_initial.py
uk_geo_utils/migrations/0002_onspd.py
uk_geo_utils/migrations/0003_auto_20171030_1504.py
uk_geo_utils/migrations/0004_auto_20180228_1553.py
uk_geo_utils/migrations/0005_onsud_ced.py
uk_geo_utils/migrations/0006_auto_20180612_1655.py
uk_geo_utils/migrations/0007_remove_onsud_ctry_flag.py
uk_geo_utils/migrations/0008_address_addressbase_postal.py
uk_geo_utils/migrations/0009_onspd_lsoa21_onspd_msoa21_onspd_oa21.py
uk_geo_utils/migrations/0010_rename_bua11_onspd_bua22_rename_nuts_onspd_itl_and_more.py
uk_geo_utils/migrations/0011_rename_bua22_onspd_bua24.py
uk_geo_utils/migrations/__init__.py
uk_geo_utils/tests/__init__.py
uk_geo_utils/tests/test_address_sorter.py
uk_geo_utils/tests/test_addressbase_geocoder.py
uk_geo_utils/tests/test_centroid.py
uk_geo_utils/tests/test_clean_addressbase_plus.py
uk_geo_utils/tests/test_clean_addressbase_standard.py
uk_geo_utils/tests/test_import_clean_addressbase_transaction_fail.py
uk_geo_utils/tests/test_import_cleaned_addresses.py
uk_geo_utils/tests/test_import_onspd.py
uk_geo_utils/tests/test_import_onsud.py
uk_geo_utils/tests/test_localauth_address_formatter.py
uk_geo_utils/tests/test_paf_address_formatter.py
uk_geo_utils/tests/test_postcode_helper.py
uk_geo_utils-0.18.0.dist-info/LICENSE
uk_geo_utils-0.18.0.dist-info/METADATA
uk_geo_utils-0.18.0.dist-info/WHEEL
uk_geo_utils-0.18.0.dist-info/top_level.txt
uk_geo_utils-0.18.0.dist-info/RECORD
