Metadata-Version: 2.2
Name: uk_geo_utils
Version: 0.18.0
Summary: Django app for working with OS Addressbase, ONSUD and ONSPD
Home-page: https://github.com/DemocracyClub/uk-geo-utils
Author: chris48s
License: MIT
Project-URL: Documentation, https://democracyclub.github.io/uk-geo-utils/
Project-URL: Source, https://github.com/DemocracyClub/uk-geo-utils
Classifier: Framework :: Django
Classifier: Framework :: Django :: 4.2
Classifier: Framework :: Django :: 5.1
Classifier: License :: OSI Approved :: MIT License
Classifier: Programming Language :: Python
Classifier: Programming Language :: Python :: 3
Classifier: Programming Language :: Python :: 3.10
Classifier: Programming Language :: Python :: 3.12
License-File: LICENSE
Requires-Dist: Django>=4.2
Requires-Dist: psycopg2-binary
Requires-Dist: psutil
Provides-Extra: development
Requires-Dist: coveralls; extra == "development"
Requires-Dist: mkdocs; extra == "development"
Requires-Dist: ruff==0.6.2; extra == "development"
Dynamic: author
Dynamic: classifier
Dynamic: description
Dynamic: description-content-type
Dynamic: home-page
Dynamic: license
Dynamic: project-url
Dynamic: provides-extra
Dynamic: requires-dist
Dynamic: summary
